plausible_proxy/__init__.py
plausible_proxy/apps.py
plausible_proxy/services.py
plausible_proxy/templatetags/__init__.py
plausible_proxy/templatetags/plausible.py
plausible_proxy/urls.py
plausible_proxy/views.py
django_plausible_proxy-0.5.1.dist-info/LICENSE
django_plausible_proxy-0.5.1.dist-info/METADATA
django_plausible_proxy-0.5.1.dist-info/WHEEL
django_plausible_proxy-0.5.1.dist-info/RECORD
