Metadata-Version: 2.1
Name: django-plausible-proxy
Version: 0.5.1
Summary: Django module to proxy requests to Plausible Analytics.
Home-page: https://github.com/imankulov/django-plausible-proxy
License: MIT
Author: Roman Imankulov
Author-email: roman.imankulov@gmail.com
Requires-Python: >=3.8,<4.0
Classifier: Development Status :: 4 - Beta
Classifier: Intended Audience :: Developers
Classifier: License :: OSI Approved :: MIT License
Classifier: Natural Language :: English
Classifier: Programming Language :: Python :: 3
Classifier: Programming Language :: Python :: 3.8
Classifier: Programming Language :: Python :: 3.9
Classifier: Programming Language :: Python :: 3.10
Classifier: Programming Language :: Python :: 3.11
Classifier: Programming Language :: Python :: 3
Classifier: Programming Language :: Python :: 3.10
Classifier: Programming Language :: Python :: 3.11
Classifier: Programming Language :: Python :: 3.8
Classifier: Programming Language :: Python :: 3.9
Requires-Dist: Django (>=3.2)
Requires-Dist: requests (>=2,<3)
